astartes/__init__.py
astartes/main.py
astartes/molecules.py
astartes/samplers/__init__.py
astartes/samplers/abstract_sampler.py
astartes/samplers/extrapolation/__init__.py
astartes/samplers/extrapolation/dbscan.py
astartes/samplers/extrapolation/kmeans.py
astartes/samplers/extrapolation/molecular_weight.py
astartes/samplers/extrapolation/optisim.py
astartes/samplers/extrapolation/scaffold.py
astartes/samplers/extrapolation/sphere_exclusion.py
astartes/samplers/extrapolation/target_property.py
astartes/samplers/extrapolation/time_based.py
astartes/samplers/interpolation/__init__.py
astartes/samplers/interpolation/kennardstone.py
astartes/samplers/interpolation/random_split.py
astartes/samplers/interpolation/spxy.py
astartes/utils/__init__.py
astartes/utils/aimsim_featurizer.py
astartes/utils/array_type_helpers.py
astartes/utils/exceptions.py
astartes/utils/fast_kennard_stone.py
astartes/utils/sampler_factory.py
astartes/utils/user_utils.py
astartes/utils/warnings.py
astartes-1.3.3.dist-info/licenses/LICENSE
astartes-1.3.3.dist-info/METADATA
astartes-1.3.3.dist-info/WHEEL
astartes-1.3.3.dist-info/top_level.txt
astartes-1.3.3.dist-info/RECORD
