Metadata-Version: 2.4
Name: astartes
Version: 1.3.3
Summary: Train:Test Algorithmic Sampling for Molecules and Arbitrary Arrays
Author-email: Jackson Burns <jwburns@mit.edu>, Himaghna Bhattacharjee <himaghna@udel.edu>, Kevin Spiekermann <kspieker@mit.edu>
License: MIT
Project-URL: Homepage, https://github.com/JacksonBurns/astartes
Classifier: Programming Language :: Python :: 3.9
Classifier: Programming Language :: Python :: 3.10
Classifier: Programming Language :: Python :: 3.11
Classifier: Programming Language :: Python :: 3.12
Requires-Python: >=3.9
License-File: LICENSE
Requires-Dist: scikit_learn
Requires-Dist: tabulate
Requires-Dist: numpy
Requires-Dist: scipy
Requires-Dist: pandas
Provides-Extra: molecules
Requires-Dist: aimsim_core; extra == "molecules"
Provides-Extra: dev
Requires-Dist: black; extra == "dev"
Requires-Dist: isort; extra == "dev"
Requires-Dist: pytest; extra == "dev"
Provides-Extra: demos
Requires-Dist: plotly; extra == "demos"
Requires-Dist: tabulate; extra == "demos"
Requires-Dist: py2opsin; extra == "demos"
Requires-Dist: kaleido; extra == "demos"
Dynamic: license-file
